kde_gpu/__init__.py
kde_gpu/__version__.py
kde_gpu/conditional_probability.py
kde_gpu/kde_gpu.py
kde_gpu/nadaraya_watson.py
kde_gpu-0.1.0.dist-info/LICENSE
kde_gpu-0.1.0.dist-info/METADATA
kde_gpu-0.1.0.dist-info/WHEEL
kde_gpu-0.1.0.dist-info/top_level.txt
kde_gpu-0.1.0.dist-info/RECORD
