Metadata-Version: 2.1
Name: kde-gpu
Version: 0.1.0
Summary: We implemented nadaraya waston kernel density and kernel conditional probability estimator using cuda through cupy. It is much faster than cpu version but it requires GPU with high memory.
Home-page: https://github.com/cc20002002/kde_gpu
Author: Chen Chen
Author-email: chen.chen.adl@gmail.com
License: MIT License
Keywords: Nadaraya-Watson,Nadaraya Watson,GPU,CUDA,cupy,kernel smoothing,conditional probability,KNN
Platform: UNKNOWN
Classifier: Development Status :: 2 - Pre-Alpha
Classifier: Operating System :: POSIX
Classifier: Natural Language :: English
Classifier: Programming Language :: Python
Classifier: Programming Language :: Python :: 3.6
Classifier: Intended Audience :: Science/Research
Classifier: Intended Audience :: Developers
Classifier: Topic :: Software Development :: Libraries :: Python Modules
Requires-Dist: numpy (>=1.14.0)
Requires-Dist: scipy (>=1.0.0)
Requires-Dist: pandas (>=0.20.2)
